README.rst
setup.py
src/krishnacalci.py
src/sivapackage.egg-info/PKG-INFO
src/sivapackage.egg-info/SOURCES.txt
src/sivapackage.egg-info/dependency_links.txt
src/sivapackage.egg-info/top_level.txt