Metadata-Version: 1.1
Name: sivapackage
Version: 0.0.1
Summary: my description
Home-page: https://cloudstones.org
Author: krishna
Author-email: cloud@cloudstones.org
License: UNKNOWN
Platform: UNKNOWN
Classifier: Programming Language :: Python :: 3
Classifier: License :: OSI Approved :: MIT License
Classifier: Operating System :: OS Independent
